opaque_ke_py-0.1.2.dist-info/METADATA
opaque_ke_py-0.1.2.dist-info/WHEEL
opaque_ke_py-0.1.2.dist-info/licenses/LICENSE
opaque_ke_py/__init__.py
opaque_ke_py/__init__.pyi
opaque_ke_py/opaque_ke_py.cpython-314t-x86_64-linux-gnu.so
opaque_ke_py/py.typed
opaque_ke_py-0.1.2.dist-info/RECORD
