Metadata-Version: 2.4
Name: opaque-ke-py
Version: 0.1.2
Classifier: Development Status :: 3 - Alpha
Classifier: Intended Audience :: Developers
Classifier: License :: OSI Approved :: MIT License
Classifier: Programming Language :: Python :: 3.12
Classifier: Programming Language :: Python :: 3.13
Classifier: Programming Language :: Python :: 3.14
Classifier: Programming Language :: Rust
Classifier: Topic :: Security :: Cryptography
License-File: LICENSE
Summary: Python bindings for the OPAQUE-KE asymmetric password-authenticated key exchange protocol
Keywords: cryptography,opaque,pake,authentication,password
License: MIT
Requires-Python: >=3.12
